homebox_client/__init__.py
homebox_client/client.py
homebox_client/errors.py
homebox_client/py.typed
homebox_client/types.py
homebox_client/api/__init__.py
homebox_client/api/actions/__init__.py
homebox_client/api/actions/post_v1_actions_create_missing_thumbnails.py
homebox_client/api/actions/post_v1_actions_ensure_asset_ids.py
homebox_client/api/actions/post_v1_actions_ensure_import_refs.py
homebox_client/api/actions/post_v1_actions_set_primary_photos.py
homebox_client/api/actions/post_v1_actions_zero_item_time_fields.py
homebox_client/api/authentication/__init__.py
homebox_client/api/authentication/get_v1_users_login_oidc.py
homebox_client/api/authentication/get_v1_users_login_oidc_callback.py
homebox_client/api/authentication/get_v1_users_refresh.py
homebox_client/api/authentication/post_v1_users_login.py
homebox_client/api/authentication/post_v1_users_logout.py
homebox_client/api/base/__init__.py
homebox_client/api/base/get_v1_currency.py
homebox_client/api/base/get_v1_status.py
homebox_client/api/group/__init__.py
homebox_client/api/group/get_v1_groups.py
homebox_client/api/group/post_v1_groups_invitations.py
homebox_client/api/group/put_v1_groups.py
homebox_client/api/item_maintenance/__init__.py
homebox_client/api/item_maintenance/get_v1_items_id_maintenance.py
homebox_client/api/item_maintenance/post_v1_items_id_maintenance.py
homebox_client/api/item_templates/__init__.py
homebox_client/api/item_templates/delete_v1_templates_id.py
homebox_client/api/item_templates/get_v1_templates.py
homebox_client/api/item_templates/get_v1_templates_id.py
homebox_client/api/item_templates/post_v1_templates.py
homebox_client/api/item_templates/post_v1_templates_id_create_item.py
homebox_client/api/item_templates/put_v1_templates_id.py
homebox_client/api/items/__init__.py
homebox_client/api/items/delete_v1_items_id.py
homebox_client/api/items/get_v1_assets_id.py
homebox_client/api/items/get_v1_items.py
homebox_client/api/items/get_v1_items_export.py
homebox_client-1.0.6.dist-info/licenses/LICENSE
homebox_client-1.0.6.dist-info/METADATA
homebox_client-1.0.6.dist-info/WHEEL
homebox_client-1.0.6.dist-info/top_level.txt
homebox_client-1.0.6.dist-info/RECORD
