Metadata-Version: 2.4
Name: homebox-client
Version: 1.0.6
Summary: Homebox API client
Author-email: pfa230 <pfa230@pfa.name>
License: MIT License
Project-URL: Homepage, https://github.com/pfa230/homebox_client
Project-URL: Source, https://github.com/pfa230/homebox_client
Project-URL: Issues, https://github.com/pfa230/homebox_client/issues
Project-URL: Documentation, https://github.com/sysadminsmedia/homebox/tree/main/docs
Keywords: OpenAPI,openapi-python-client,Homebox API
Classifier: Development Status :: 4 - Beta
Classifier: Intended Audience :: Developers
Classifier: License :: OSI Approved :: MIT License
Classifier: Programming Language :: Python :: 3
Classifier: Programming Language :: Python :: 3 :: Only
Classifier: Programming Language :: Python :: 3.9
Classifier: Programming Language :: Python :: 3.10
Classifier: Programming Language :: Python :: 3.11
Classifier: Programming Language :: Python :: 3.12
Classifier: Programming Language :: Python :: 3.13
Classifier: Typing :: Typed
Requires-Python: >=3.9
License-File: LICENSE
Requires-Dist: attrs>=22.2.0
Requires-Dist: httpx<0.29.0,>=0.23.0
Dynamic: license-file
